amdt/__init__.py
amdt/eagar_tsai.py
amdt/gcode_segmenter.py
amdt/simulator.py
amdt-0.0.3.dist-info/METADATA
amdt-0.0.3.dist-info/WHEEL
amdt-0.0.3.dist-info/top_level.txt
amdt-0.0.3.dist-info/RECORD
